neatify/__init__.py
neatify/checkpoint.py
neatify/core.py
neatify/evolution.py
neatify/population.py
neatify/pytorch_adapter.py
neatify/visualization.py
neatify/distributed/__init__.py
neatify/distributed/config.py
neatify/distributed/master.py
neatify/distributed/protocol.py
neatify/distributed/worker.py
neatify_ai-0.1.4.dist-info/licenses/LICENSE
neatify_ai-0.1.4.dist-info/METADATA
neatify_ai-0.1.4.dist-info/WHEEL
neatify_ai-0.1.4.dist-info/top_level.txt
neatify_ai-0.1.4.dist-info/RECORD
