Metadata-Version: 2.4
Name: neatify-ai
Version: 0.1.4
Summary: A lightweight NEAT library with PyTorch integration
Author-email: Supreme Shrestha <shrestharhythm@gmail.com>, Bishesh Marasini <marasinibishesh@gmail.com>, Shova Gelal <shovagelal33@gmail.com>, Bhawana Ojha <bhawanaojha48@gmail.com>
License: MIT License
Project-URL: Homepage, https://github.com/Supreme-Shrestha/neatify-ai
Project-URL: Repository, https://github.com/Supreme-Shrestha/neatify-ai
Keywords: neat,evolutionary,neural-networks,pytorch,distributed
Classifier: Development Status :: 4 - Beta
Classifier: Intended Audience :: Science/Research
Classifier: License :: OSI Approved :: MIT License
Classifier: Programming Language :: Python :: 3
Classifier: Programming Language :: Python :: 3.8
Classifier: Programming Language :: Python :: 3.9
Classifier: Programming Language :: Python :: 3.10
Classifier: Programming Language :: Python :: 3.11
Classifier: Topic :: Scientific/Engineering :: Artificial Intelligence
Requires-Python: >=3.8
License-File: LICENSE
Requires-Dist: torch
Requires-Dist: numpy
Requires-Dist: matplotlib
Requires-Dist: networkx
Dynamic: license-file
